{
    "application_name": "6000_6000",
    "optimization_objectives": ["distance"],
    "log_file": "hm_placer_min.log",
    "output_data_file": "hm_placer_min.csv",
	"design_of_experiment": {
        "doe_type": "random sampling",
        "number_of_samples": 6000
    },
    "optimization_iterations": 6000,
    "input_parameters" : {
        "0": {
            "parameter_type": "categorical",
            "values": 
                ["0", "1", "2", "3" , "4", "5", "6", "7", "8", "9", 
            	"10", "11", "12", "13" , "14", "15", "16", "17", "18", "19", 
            	"20", "21", "22", "23" , "24", "25", "26", "27", "28", "29", 
            	"30", "31", "32", "33" , "34", "35", "36", "37", "38", "39", 
            	"40", "41", "42", "43" , "44", "45", "46", "47", "48", "49", 
            	"50", "51", "52", "53" , "54", "55", "56", "57", "58", "59", 
            	"60", "61", "62", "63"]
           },
        "1": {
            "parameter_type": "categorical",
            "values": 
                ["0", "1", "2", "3" , "4", "5", "6", "7", "8", "9", 
            	"10", "11", "12", "13" , "14", "15", "16", "17", "18", "19", 
            	"20", "21", "22", "23" , "24", "25", "26", "27", "28", "29", 
            	"30", "31", "32", "33" , "34", "35", "36", "37", "38", "39", 
            	"40", "41", "42", "43" , "44", "45", "46", "47", "48", "49", 
            	"50", "51", "52", "53" , "54", "55", "56", "57", "58", "59", 
            	"60", "61", "62", "63"]
           },
        "2": {
            "parameter_type": "categorical",
            "values": 
                ["0", "1", "2", "3" , "4", "5", "6", "7", "8", "9", 
            	"10", "11", "12", "13" , "14", "15", "16", "17", "18", "19", 
            	"20", "21", "22", "23" , "24", "25", "26", "27", "28", "29", 
            	"30", "31", "32", "33" , "34", "35", "36", "37", "38", "39", 
            	"40", "41", "42", "43" , "44", "45", "46", "47", "48", "49", 
            	"50", "51", "52", "53" , "54", "55", "56", "57", "58", "59", 
            	"60", "61", "62", "63"]
           },
        "3": {
            "parameter_type": "categorical",
            "values": 
                ["0", "1", "2", "3" , "4", "5", "6", "7", "8", "9", 
            	"10", "11", "12", "13" , "14", "15", "16", "17", "18", "19", 
            	"20", "21", "22", "23" , "24", "25", "26", "27", "28", "29", 
            	"30", "31", "32", "33" , "34", "35", "36", "37", "38", "39", 
            	"40", "41", "42", "43" , "44", "45", "46", "47", "48", "49", 
            	"50", "51", "52", "53" , "54", "55", "56", "57", "58", "59", 
            	"60", "61", "62", "63"]
           },
        "4": {
            "parameter_type": "categorical",
            "values": 
                ["0", "1", "2", "3" , "4", "5", "6", "7", "8", "9", 
            	"10", "11", "12", "13" , "14", "15", "16", "17", "18", "19", 
            	"20", "21", "22", "23" , "24", "25", "26", "27", "28", "29", 
            	"30", "31", "32", "33" , "34", "35", "36", "37", "38", "39", 
            	"40", "41", "42", "43" , "44", "45", "46", "47", "48", "49", 
            	"50", "51", "52", "53" , "54", "55", "56", "57", "58", "59", 
            	"60", "61", "62", "63"]
           },
        "5": {
            "parameter_type": "categorical",
            "values": 
                ["0", "1", "2", "3" , "4", "5", "6", "7", "8", "9", 
            	"10", "11", "12", "13" , "14", "15", "16", "17", "18", "19", 
            	"20", "21", "22", "23" , "24", "25", "26", "27", "28", "29", 
            	"30", "31", "32", "33" , "34", "35", "36", "37", "38", "39", 
            	"40", "41", "42", "43" , "44", "45", "46", "47", "48", "49", 
            	"50", "51", "52", "53" , "54", "55", "56", "57", "58", "59", 
            	"60", "61", "62", "63"]
           },
        "6": {
            "parameter_type": "categorical",
            "values": 
                ["0", "1", "2", "3" , "4", "5", "6", "7", "8", "9", 
            	"10", "11", "12", "13" , "14", "15", "16", "17", "18", "19", 
            	"20", "21", "22", "23" , "24", "25", "26", "27", "28", "29", 
            	"30", "31", "32", "33" , "34", "35", "36", "37", "38", "39", 
            	"40", "41", "42", "43" , "44", "45", "46", "47", "48", "49", 
            	"50", "51", "52", "53" , "54", "55", "56", "57", "58", "59", 
            	"60", "61", "62", "63"]
           },
        "7": {
            "parameter_type": "categorical",
            "values": 
                ["0", "1", "2", "3" , "4", "5", "6", "7", "8", "9", 
            	"10", "11", "12", "13" , "14", "15", "16", "17", "18", "19", 
            	"20", "21", "22", "23" , "24", "25", "26", "27", "28", "29", 
            	"30", "31", "32", "33" , "34", "35", "36", "37", "38", "39", 
            	"40", "41", "42", "43" , "44", "45", "46", "47", "48", "49", 
            	"50", "51", "52", "53" , "54", "55", "56", "57", "58", "59", 
            	"60", "61", "62", "63"]
           },
        "8": {
            "parameter_type": "categorical",
            "values": 
                ["0", "1", "2", "3" , "4", "5", "6", "7", "8", "9", 
            	"10", "11", "12", "13" , "14", "15", "16", "17", "18", "19", 
            	"20", "21", "22", "23" , "24", "25", "26", "27", "28", "29", 
            	"30", "31", "32", "33" , "34", "35", "36", "37", "38", "39", 
            	"40", "41", "42", "43" , "44", "45", "46", "47", "48", "49", 
            	"50", "51", "52", "53" , "54", "55", "56", "57", "58", "59", 
            	"60", "61", "62", "63"]
           },
        "9": {
            "parameter_type": "categorical",
            "values": 
                ["0", "1", "2", "3" , "4", "5", "6", "7", "8", "9", 
            	"10", "11", "12", "13" , "14", "15", "16", "17", "18", "19", 
            	"20", "21", "22", "23" , "24", "25", "26", "27", "28", "29", 
            	"30", "31", "32", "33" , "34", "35", "36", "37", "38", "39", 
            	"40", "41", "42", "43" , "44", "45", "46", "47", "48", "49", 
            	"50", "51", "52", "53" , "54", "55", "56", "57", "58", "59", 
            	"60", "61", "62", "63"]
           },
        "10": {
            "parameter_type": "categorical",
            "values": 
                ["0", "1", "2", "3" , "4", "5", "6", "7", "8", "9", 
            	"10", "11", "12", "13" , "14", "15", "16", "17", "18", "19", 
            	"20", "21", "22", "23" , "24", "25", "26", "27", "28", "29", 
            	"30", "31", "32", "33" , "34", "35", "36", "37", "38", "39", 
            	"40", "41", "42", "43" , "44", "45", "46", "47", "48", "49", 
            	"50", "51", "52", "53" , "54", "55", "56", "57", "58", "59", 
            	"60", "61", "62", "63"]
           },
        "11": {
            "parameter_type": "categorical",
            "values": 
                ["0", "1", "2", "3" , "4", "5", "6", "7", "8", "9", 
            	"10", "11", "12", "13" , "14", "15", "16", "17", "18", "19", 
            	"20", "21", "22", "23" , "24", "25", "26", "27", "28", "29", 
            	"30", "31", "32", "33" , "34", "35", "36", "37", "38", "39", 
            	"40", "41", "42", "43" , "44", "45", "46", "47", "48", "49", 
            	"50", "51", "52", "53" , "54", "55", "56", "57", "58", "59", 
            	"60", "61", "62", "63"]
           },
        "12": {
            "parameter_type": "categorical",
            "values": 
                ["0", "1", "2", "3" , "4", "5", "6", "7", "8", "9", 
            	"10", "11", "12", "13" , "14", "15", "16", "17", "18", "19", 
            	"20", "21", "22", "23" , "24", "25", "26", "27", "28", "29", 
            	"30", "31", "32", "33" , "34", "35", "36", "37", "38", "39", 
            	"40", "41", "42", "43" , "44", "45", "46", "47", "48", "49", 
            	"50", "51", "52", "53" , "54", "55", "56", "57", "58", "59", 
            	"60", "61", "62", "63"]
           },
        "13": {
            "parameter_type": "categorical",
            "values": 
                ["0", "1", "2", "3" , "4", "5", "6", "7", "8", "9", 
            	"10", "11", "12", "13" , "14", "15", "16", "17", "18", "19", 
            	"20", "21", "22", "23" , "24", "25", "26", "27", "28", "29", 
            	"30", "31", "32", "33" , "34", "35", "36", "37", "38", "39", 
            	"40", "41", "42", "43" , "44", "45", "46", "47", "48", "49", 
            	"50", "51", "52", "53" , "54", "55", "56", "57", "58", "59", 
            	"60", "61", "62", "63"]
           },
        "14": {
            "parameter_type": "categorical",
            "values": 
                ["0", "1", "2", "3" , "4", "5", "6", "7", "8", "9", 
            	"10", "11", "12", "13" , "14", "15", "16", "17", "18", "19", 
            	"20", "21", "22", "23" , "24", "25", "26", "27", "28", "29", 
            	"30", "31", "32", "33" , "34", "35", "36", "37", "38", "39", 
            	"40", "41", "42", "43" , "44", "45", "46", "47", "48", "49", 
            	"50", "51", "52", "53" , "54", "55", "56", "57", "58", "59", 
            	"60", "61", "62", "63"]
           },
        "15": {
            "parameter_type": "categorical",
            "values": 
                ["0", "1", "2", "3" , "4", "5", "6", "7", "8", "9", 
            	"10", "11", "12", "13" , "14", "15", "16", "17", "18", "19", 
            	"20", "21", "22", "23" , "24", "25", "26", "27", "28", "29", 
            	"30", "31", "32", "33" , "34", "35", "36", "37", "38", "39", 
            	"40", "41", "42", "43" , "44", "45", "46", "47", "48", "49", 
            	"50", "51", "52", "53" , "54", "55", "56", "57", "58", "59", 
            	"60", "61", "62", "63"]
           },
        "16": {
            "parameter_type": "categorical",
            "values": 
                ["0", "1", "2", "3" , "4", "5", "6", "7", "8", "9", 
            	"10", "11", "12", "13" , "14", "15", "16", "17", "18", "19", 
            	"20", "21", "22", "23" , "24", "25", "26", "27", "28", "29", 
            	"30", "31", "32", "33" , "34", "35", "36", "37", "38", "39", 
            	"40", "41", "42", "43" , "44", "45", "46", "47", "48", "49", 
            	"50", "51", "52", "53" , "54", "55", "56", "57", "58", "59", 
            	"60", "61", "62", "63"]
           },
        "17": {
            "parameter_type": "categorical",
            "values": 
                ["0", "1", "2", "3" , "4", "5", "6", "7", "8", "9", 
            	"10", "11", "12", "13" , "14", "15", "16", "17", "18", "19", 
            	"20", "21", "22", "23" , "24", "25", "26", "27", "28", "29", 
            	"30", "31", "32", "33" , "34", "35", "36", "37", "38", "39", 
            	"40", "41", "42", "43" , "44", "45", "46", "47", "48", "49", 
            	"50", "51", "52", "53" , "54", "55", "56", "57", "58", "59", 
            	"60", "61", "62", "63"]
           },
        "18": {
            "parameter_type": "categorical",
            "values": 
                ["0", "1", "2", "3" , "4", "5", "6", "7", "8", "9", 
            	"10", "11", "12", "13" , "14", "15", "16", "17", "18", "19", 
            	"20", "21", "22", "23" , "24", "25", "26", "27", "28", "29", 
            	"30", "31", "32", "33" , "34", "35", "36", "37", "38", "39", 
            	"40", "41", "42", "43" , "44", "45", "46", "47", "48", "49", 
            	"50", "51", "52", "53" , "54", "55", "56", "57", "58", "59", 
            	"60", "61", "62", "63"]
           },
        "19": {
            "parameter_type": "categorical",
            "values": 
                ["0", "1", "2", "3" , "4", "5", "6", "7", "8", "9", 
            	"10", "11", "12", "13" , "14", "15", "16", "17", "18", "19", 
            	"20", "21", "22", "23" , "24", "25", "26", "27", "28", "29", 
            	"30", "31", "32", "33" , "34", "35", "36", "37", "38", "39", 
            	"40", "41", "42", "43" , "44", "45", "46", "47", "48", "49", 
            	"50", "51", "52", "53" , "54", "55", "56", "57", "58", "59", 
            	"60", "61", "62", "63"]
           }
    }
}
